{
  "asset": "silver",
  "started_at": "2026-07-01T13:40:07.909758",
  "status": "success",
  "data_rows": 6859,
  "train_rows": 4801,
  "val_rows": 1029,
  "test_rows": 1029,
  "feature_count": 89,
  "best_params": {
    "max_depth": 4,
    "lr": 0.03541732429168535,
    "sub": 0.7220499540409457,
    "col": 0.5022530353792904
  },
  "accuracy": 0.7298347910592808,
  "model_path": "models/processed/silver_model_enhanced.pkl",
  "completed_at": "2026-07-01T13:41:43.339235",
  "duration_seconds": 95.43
}